{"levels":[{"moves":22,"score":165,"colors":["a","b","d","e","w"],"bundles":["gum","barrier","transporter","clock"],"field":["3k2a2ke2kbab2kw2kb3k2b","2kaeabwwa2kb","2kddeeaad2kw","dwd7uabwdedubdb","wbduudba","2keabawbw2kd","2kwbdabwd2ka","3k2e2ka2keda2kb2ke3k2e"],"floor":["        ","        ","  2>22>32>32>3  ","  2>2  2>0  ","  2>2  2>0  ","  2>12>12>12>0  ","        ","        "],"barriers":[[[1,2],[1,3],[1,4],[1,5],[5,2],[5,3],[5,4],[5,5]],[[2,1],[2,5],[3,1],[3,5],[4,1],[4,5],[5,1],[5,5]]],"goals":[{"type":"clock","target":6},{"type":"gum","target":20}],"tutorial":[{"light":[[4,2],[5,2],[6,1],[6,2]],"control":[[6,1],[6,2]],"textBlock":{"text":"messages:level1576TutorialStep1"}}],"version":0,"stars":100,"hard":false,"episodeNo":105,"levelNo":0},{"moves":33,"score":160,"colors":["a","B","d","e","w"],"bundles":["clock","rug","dirt","dirt_maker"],"field":["   ....4ubweu"," 4udbau....uu"," uu..2%....","....2%.2%.2%...","...2%.2q12%....","..2%.2%.2%.....","...2%...4uaewu ","4uwadu....uu ","uu....   "],"floor":["       ||"," ||    ||"," ||      ","    |    ","   |||   ","    |    ","      || ","||    || ","||       "],"goals":[{"type":"clock","target":12},{"type":"|","target":70},{"type":"b","target":50}],"version":0,"stars":100,"hard":false,"episodeNo":105,"levelNo":1},{"moves":29,"score":160,"colors":["a","b","D","e","w"],"bundles":["gum","firefly_jar","dragon"],"field":[".....2k.2v22k.",".....2v32k.2v3",".....2k.2v22k.","3k2.3k2.3k2.3U35U2v32k.2v3","2v32k.2v3UU3k2.3k2.3k2.","2k.2v22k......","2v32k.2v3.....","2k.2v22k......"],"floor":["        ","        ","        ","GGGGGGGG","GGGGGGGG","        ","        ","        "],"goals":[{"type":"dragon_cell","target":1},{"type":"firefly_jar_cell","target":32},{"type":"d","target":70}],"version":0,"stars":100,"hard":false,"episodeNo":105,"levelNo":2},{"moves":34,"score":150,"colors":["b","c","d","e","w"],"bundles":["truffle","rabbit","lollipop","barrier"],"field":["3Qb.2Oc4-Qw.2Oc4-Qe.2Oc4-Qd.2Oc3Qe.","2Oc4-Qe.2Oc4-Qd.2Oc4-Qb.2Oc4-Qe.2Oc","3Qe.2Oc4-Qd.2Oc4-Qe.2Oc4-Qw.2Oc3Qb.","         "," weewwbw "," dwdbebd "," ccbdeew "," ebcbwd. "," dweedwd "],"floor":["2T1TT2T1TT2T2TT","T2T2TTTTTT2T1","TTTT2T1T2T1TT","         "," 2T13Tl23Tl23Tl22T13Tl23Tl2 "," 3Tl23Tl24T2l23Tl23Tl23Tl22T1 "," 3Tl22T13Tl23Tl23Tl22T13Tl2 "," 2T2T3Tl23Tl23Tl22T2T "," TT3Tl23Tl22T1TT "],"barriers":[[[2,0],[2,1],[2,3],[2,4],[2,5],[2,7],[2,8]],[]],"goals":[{"type":"truffle","target":14},{"type":"lollipop","target":30,"createOnCollect":{"type":"O.","amount":17}},{"type":"rabbit","target":16}],"version":1,"stars":100,"hard":false,"episodeNo":105,"levelNo":3},{"moves":29,"score":155,"colors":["a","b","c","d","e"],"bundles":["barrier","colorcookieman","bag","waffle","color_container"],"field":["  a   2-a  ","  *   *  "," 3-Va 3-Va 3-Va 3-Va ","3-Va3^a.2Sa3^c.2Sa3^c.2Sa.3-Va"," 2Sa3^ag2Sc3^ag2Sc3^ag2Sa ","3-Va3^c.2Sc3^cg 3^cg2Sc3^c.3-Va"," 2Sa3^ag2Sc3^ag2Sc3^ag2Sa ","3-Va3^a.2Sa3^c.2Sa3^c.2Sa3^a.3-Va"," 3-Va 3-Va 3-Va 3-Va "],"floor":["         ","         ","         ","         ","         ","         ","         ","         ","         "],"goals":[{"type":"color_cookie_man","target":30,"createOnCollect":{"type":"V.","amount":16}},{"type":"color_container","target":12,"createOnCollect":{"type":"g","amount":4}},{"type":"waffle","target":30,"createOnCollect":{"type":"S.","amount":14}}],"version":1,"stars":100,"hard":true,"episodeNo":105,"levelNo":4,"barriers":[[[1,2],[1,6]],[]]},{"moves":18,"score":165,"colors":["a","b","d","e","w"],"bundles":["gum","transporter","clock"],"field":["3k.!2.!3k.!2.!2.!3k.!2.!3k.!","2.!3k.!2.!2.!2.!2.!3k.!2.!","3k.!2.!3-2d2-w2-a3-2b2.!3k.!","2.!2.!2-e9uwbedewdau2-w2.!2.!","2.!2.!2-duu2-e2.!2.!","3k.!2.!3-2b2-a2-w3-2d2.!3k.!","2.!3k.!2.!2.!2.!2.!3k.!2.!","3k.!2.!3k.!2.!2.!3k.!2.!3k.!"],"floor":["2>22>32>32>32>32>32>32>3","2>22>12>12>12>12>12>22>0","2>22>0    2>22>0","2>22>0    2>22>0","2>22>0    2>22>0","2>22>0    2>22>0","2>22>02>32>32>32>32>32>0","2>12>12>12>12>12>12>12>0"],"goals":[{"type":"clock","target":8},{"type":"!","target":48}],"version":1,"stars":100,"hard":false,"episodeNo":105,"levelNo":5},{"moves":33,"score":150,"colors":["a","b","c","d","E","w"],"bundles":["bomb","transporter","barrier","muffin","ice"],"field":["4Zy.9...5Zy.10...4Zy.9","         ","2L1.......2L1",".........",".2L1.2L12I12L1.2L1.","2L12I12L12I12L12I12L12I12L1",".2L1.2L12I12L1.2L1.",".........","2L1.......2L1"],"floor":["2>12>12>12>12>12>12>12>12>1","         "," @@@@@@@ ","@@@@@@@@@","@ @   @ @","         ","@ @   @ @","@@@@@@@@@"," @@@@@@@ "],"goals":[{"type":"muffin_goal_cell","target":17},{"type":"@","target":40},{"type":"e","target":50}],"version":1,"stars":100,"hard":false,"episodeNo":105,"levelNo":6,"barriers":[[[0,0],[0,2],[0,4],[0,6],[0,8]],[]]},{"moves":24,"score":175,"colors":["b","c","d","w"],"bundles":["firefly_jar","barrier","dog","ice_cream_maker"],"field":[" 2v6e2v4e2v4e  "," e2v3e2v3e2v4  "," 2v4e2v3*2v3e  "," e2v43y27ye2v6  ","   yy    ","........ ",".2i2...... ","......2i2. ","........ "],"floor":["         ","         ","         ","         ","         ","         ","         ","         ","         "],"goals":[{"type":"dog_cell","target":1},{"type":"firefly_jar_cell","target":44}],"version":1,"stars":100,"hard":false,"episodeNo":105,"levelNo":7,"barriers":[[[3,1],[3,2],[3,5],[3,6],[4,3],[4,4]],[]]},{"moves":24,"score":185,"colors":["A","B","e","w"],"bundles":["gum"],"field":["  2f22f22f22f22f2  "," 2f2.....2f2 "," 2f2.. ..2f2 "," 2f2.. ..2f2 "," 2f2.....2f2 ","  2f2...2f2  ","2f2  4k2f12k.4k2f1  2f2","  4k2f14kRy.4k3f34kRy.4k2f1  ","2f2 4k2f14kRy.4kRx.4kRy.4k2f1 2f2"],"floor":["         ","   GGG   ","   G G   ","   G G   ","   GGG   ","         ","         ","  GGGGG  ","  GGGGG  "],"goals":[{"type":"flower_cell","target":26},{"type":"a","target":120},{"type":"b","target":120}],"version":1,"stars":100,"hard":false,"episodeNo":105,"levelNo":8},{"moves":30,"score":170,"colors":["b","c","d","e","w"],"bundles":["crab","lollipop","rug"],"field":["3&O....3&O....3&O.","... ... .",". ... 3&O...",".........",".3&O.. 3&O... .","........3&O.","3&O. ... ...","... 3&O... .","..3&O.....3&O.."],"floor":["||     ||","|       |","         ","   ||    ","    |    ","    ||   ","         ","|       |","||     ||"],"goals":[{"type":"|","target":71},{"type":"lollipop","target":30,"createOnCollect":{"type":"O.","amount":19}}],"version":1,"hard":false,"stars":100,"episodeNo":105,"levelNo":9},{"moves":32,"score":160,"colors":["c","d","e","w"],"bundles":["dirty_honey","truffle","cake"],"field":[" 3oQ........","3oQ....  ...","..KK.  ..","..KK2Q.  ..","..2o.2Q.3oQ.2Q.2o...","..  2Q.KK..","..  .KK..","...  ...3oQ.",".......3oQ. "],"floor":[" zzzzzzzz","zzzz  zzz","zzzzz  zz","zzzzz  zz","zzzzzzzzz","zz  zzzzz","zz  zzzzz","zzz  zzzz","zzzzzzzz "],"goals":[{"type":"cake_cell","target":24},{"type":"dirty_honey","target":67},{"type":"truffle","target":9}],"version":0,"stars":100,"hard":false,"episodeNo":105,"levelNo":10},{"moves":29,"score":190,"colors":["b","c","d","e","w"],"bundles":["firefly_jar","rabbit"],"field":["2v2  ...  2v2"," ....... "," ...2v3... ","...3kv15k2Rx.3kv1...","..2v35k2Ry. 5k2Ry.2v3..","...3kv15k2Rx.3kv1..."," ...2v3... "," ....... ","2v2  ...  2v2"],"floor":["   4T2l23Tl2T   "," 4T1l23Tl23Tl23Tl2TTT "," 3Tl23Tl2T4T1l24T2l23Tl23Tl2 ","3Tl2T4T2l23Tl2T3Tl23Tl2T3Tl2","TT3Tl23Tl2 3Tl23Tl23Tl24T1l2","TT4T1l2T3Tl23Tl2TTT"," 3Tl23Tl2T3Tl23Tl24T2l23Tl2 "," T3Tl24T1l2TT3Tl23Tl2 ","   3Tl23Tl24T1l2   "],"goals":[{"type":"firefly_jar_cell","target":24},{"type":"rabbit","target":10}],"version":1,"stars":100,"hard":true,"episodeNo":105,"levelNo":11},{"moves":22,"score":200,"colors":["B","d","E","w"],"bundles":["dirt","dirt_maker","muffin","bag","bomb"],"field":["..2%.2%.    2q2",". .2%.2%.    ","....2%.2%.   ","2L1....2%.2%.  ","4^.L12I1.. .2%.2%. ","2I14^.I12L1....2%.2%.","4^.L12L1 2L1....2%.","2L14^.I12L14^.L12I1.. .","5Zx.222L14^.I12L14^.L12I1..."],"floor":["         ","         ","         ","         ","G        ","GG       ","GG       ","GGGG     ","GGGGG    "],"goals":[{"type":"muffin_goal_cell","target":12},{"type":"b","target":90},{"type":"e","target":90}],"version":1,"stars":100,"hard":false,"episodeNo":105,"levelNo":12},{"moves":25,"score":180,"colors":["a","b","c","D","w"],"bundles":["gum"],"field":["3k3.2f1...    ","2f13k2.... 2f1 2f1","3k3.2f1....2k.2k.2k.","2f13k2.....3k2.2k.3k2.","3k3.2f1....3k2.2k.3k2.","2f13k2.....2k.2k.2k.","3k3.2f1... 2f1 2f1","2f13k2....    ","         "],"floor":["         ","         ","         ","         ","         ","         ","         ","         ","         "],"goals":[{"type":"gum","target":20},{"type":"flower_cell","target":12},{"type":"d","target":50}],"version":1,"stars":100,"hard":false,"episodeNo":105,"levelNo":13},{"moves":28,"score":160,"colors":["b","d","e","w"],"bundles":["ice","muffin","donut_box"],"field":["2-a2L12L12L12L12L12L12-a",".2-a2L12L12L12L12-a.","..2-a2L12L12-a..","...2p32-a...","...2-a2p2...","..2-a..2-a..",".2-a....2-a.","a......a"],"floor":["@@@@@@@@","@@@@@@@@","@@@@@@@@","@@@ @@@@","@@@@ @@@","@@@@@@@@","@@@@@@@@","@@@@@@@@"],"goals":[{"type":"muffin_goal_cell","target":12},{"type":"@","target":62}],"version":1,"hard":false,"stars":100,"episodeNo":105,"levelNo":14}]}