{"cake_splash_json":{"skeleton":{"hash":"e5RtEZ1ra5eiozk6H+80In9Eibw","spine":"3.5.35","width":70.8,"height":46.69},"bones":[{"name":"root","x":0.03,"y":-6.63},{"name":"bone2","parent":"root","rotation":1.21,"x":-0.56,"y":17.99,"scaleX":0.525,"scaleY":0.525},{"name":"cake_splash","parent":"bone2","length":40.89,"rotation":167.32,"x":-17.85,"y":3.83},{"name":"cake_splash2","parent":"bone2","length":40.89,"rotation":16.1,"x":23.87,"y":2.21}],"slots":[{"name":"cake_splash","bone":"cake_splash","attachment":"cake_splash"},{"name":"cake_splash2","bone":"cake_splash2","attachment":"cake_splash"}],"skins":{"default":{"cake_splash":{"cake_splash":{"x":11.11,"y":0.66,"rotation":-16.1,"width":58,"height":70}},"cake_splash2":{"cake_splash":{"x":11.11,"y":0.66,"rotation":-16.1,"width":58,"height":70}}}},"animations":{"animation":{"slots":{"cake_splash":{"color":[{"time":0,"color":"ffffff00"},{"time":0.0333,"color":"ffffffff","curve":"stepped"},{"time":0.2667,"color":"ffffffff"},{"time":0.3,"color":"ffffff00"}]},"cake_splash2":{"color":[{"time":0,"color":"ffffff00"},{"time":0.0333,"color":"ffffffff","curve":"stepped"},{"time":0.2667,"color":"ffffffff"},{"time":0.3,"color":"ffffff00"}]}},"bones":{"root":{"rotate":[{"time":0,"angle":0}],"translate":[{"time":0,"x":0,"y":0}],"scale":[{"time":0,"x":1,"y":1}],"shear":[{"time":0,"x":0,"y":0}]},"bone2":{"rotate":[{"time":0,"angle":0}],"translate":[{"time":0,"x":1.02,"y":-1.15}],"scale":[{"time":0,"x":0.252,"y":0.252},{"time":0.1667,"x":2.619,"y":2.619}],"shear":[{"time":0,"x":0,"y":0}]},"cake_splash":{"rotate":[{"time":0,"angle":0}],"translate":[{"time":0,"x":0,"y":0},{"time":0.3,"x":-26.91,"y":-1.67}],"scale":[{"time":0,"x":1,"y":1},{"time":0.1333,"x":1.27,"y":1},{"time":0.3333,"x":0.263,"y":1}],"shear":[{"time":0,"x":0,"y":0}]},"cake_splash2":{"rotate":[{"time":0,"angle":0}],"translate":[{"time":0,"x":0,"y":0},{"time":0.3,"x":22.39,"y":-0.47}],"scale":[{"time":0,"x":1,"y":1},{"time":0.1,"x":1.27,"y":1},{"time":0.2667,"x":0.537,"y":1,"curve":"stepped"},{"time":0.3,"x":0.537,"y":1}],"shear":[{"time":0,"x":0,"y":0}]}},"drawOrder":[{"time":0}]}}},"plist":"<?xml version=\"1.0\" encoding=\"UTF-8\"?>\n<!DOCTYPE plist PUBLIC \"-//Apple Computer//DTD PLIST 1.0//EN\" \"http://www.apple.com/DTDs/PropertyList-1.0.dtd\">\n<plist version=\"1.0\">\n    <dict>\n        <key>frames</key>\n        <dict>\n            <key>cake-images-cake_1_1.png</key>\n            <dict>\n                <key>aliases</key>\n                <array/>\n                <key>spriteOffset</key>\n                <string>{0,0}</string>\n                <key>spriteSize</key>\n                <string>{124,129}</string>\n                <key>spriteSourceSize</key>\n                <string>{124,129}</string>\n                <key>textureRect</key>\n                <string>{{244,1},{124,129}}</string>\n                <key>textureRotated</key>\n                <false/>\n            </dict>\n            <key>cake-images-cake_1_2.png</key>\n            <dict>\n                <key>aliases</key>\n                <array/>\n                <key>spriteOffset</key>\n                <string>{0,0}</string>\n                <key>spriteSize</key>\n                <string>{124,129}</string>\n                <key>spriteSourceSize</key>\n                <string>{124,129}</string>\n                <key>textureRect</key>\n                <string>{{370,1},{124,129}}</string>\n                <key>textureRotated</key>\n                <false/>\n            </dict>\n            <key>cake-images-cake_1_3.png</key>\n            <dict>\n                <key>aliases</key>\n                <array/>\n                <key>spriteOffset</key>\n                <string>{0,0}</string>\n                <key>spriteSize</key>\n                <string>{124,129}</string>\n                <key>spriteSourceSize</key>\n                <string>{124,129}</string>\n                <key>textureRect</key>\n                <string>{{244,132},{124,129}}</string>\n                <key>textureRotated</key>\n                <false/>\n            </dict>\n            <key>cake-images-cake_2_1.png</key>\n            <dict>\n                <key>aliases</key>\n                <array/>\n                <key>spriteOffset</key>\n                <string>{0,0}</string>\n                <key>spriteSize</key>\n                <string>{123,127}</string>\n                <key>spriteSourceSize</key>\n                <string>{123,127}</string>\n                <key>textureRect</key>\n                <string>{{1,394},{123,127}}</string>\n                <key>textureRotated</key>\n                <false/>\n            </dict>\n            <key>cake-images-cake_2_2.png</key>\n            <dict>\n                <key>aliases</key>\n                <array/>\n                <key>spriteOffset</key>\n                <string>{0,0}</string>\n                <key>spriteSize</key>\n                <string>{123,127}</string>\n                <key>spriteSourceSize</key>\n                <string>{123,127}</string>\n                <key>textureRect</key>\n                <string>{{311,282},{123,127}}</string>\n                <key>textureRotated</key>\n                <false/>\n            </dict>\n            <key>cake-images-cake_2_3.png</key>\n            <dict>\n                <key>aliases</key>\n                <array/>\n                <key>spriteOffset</key>\n                <string>{0,0}</string>\n                <key>spriteSize</key>\n                <string>{123,127}</string>\n                <key>spriteSourceSize</key>\n                <string>{123,127}</string>\n                <key>textureRect</key>\n                <string>{{311,411},{123,127}}</string>\n                <key>textureRotated</key>\n                <false/>\n            </dict>\n            <key>cake-images-cake_3_1.png</key>\n            <dict>\n                <key>aliases</key>\n                <array/>\n                <key>spriteOffset</key>\n                <string>{0,0}</string>\n                <key>spriteSize</key>\n                <string>{122,150}</string>\n                <key>spriteSourceSize</key>\n                <string>{122,150}</string>\n                <key>textureRect</key>\n                <string>{{1,523},{122,150}}</string>\n                <key>textureRotated</key>\n                <false/>\n            </dict>\n            <key>cake-images-cake_3_2.png</key>\n            <dict>\n                <key>aliases</key>\n                <array/>\n                <key>spriteOffset</key>\n                <string>{0,0}</string>\n                <key>spriteSize</key>\n                <string>{122,150}</string>\n                <key>spriteSourceSize</key>\n                <string>{122,150}</string>\n                <key>textureRect</key>\n                <string>{{251,540},{122,150}}</string>\n                <key>textureRotated</key>\n                <false/>\n            </dict>\n            <key>cake-images-cake_3_3.png</key>\n            <dict>\n                <key>aliases</key>\n                <array/>\n                <key>spriteOffset</key>\n                <string>{0,0}</string>\n                <key>spriteSize</key>\n                <string>{122,150}</string>\n                <key>spriteSourceSize</key>\n                <string>{122,150}</string>\n                <key>textureRect</key>\n                <string>{{125,542},{122,150}}</string>\n                <key>textureRotated</key>\n                <false/>\n            </dict>\n            <key>cake-images-cake_4_1.png</key>\n            <dict>\n                <key>aliases</key>\n                <array/>\n                <key>spriteOffset</key>\n                <string>{0,0}</string>\n                <key>spriteSize</key>\n                <string>{123,148}</string>\n                <key>spriteSourceSize</key>\n                <string>{123,148}</string>\n                <key>textureRect</key>\n                <string>{{370,132},{123,148}}</string>\n                <key>textureRotated</key>\n                <false/>\n            </dict>\n            <key>cake-images-cake_4_2.png</key>\n            <dict>\n                <key>aliases</key>\n                <array/>\n                <key>spriteOffset</key>\n                <string>{0,0}</string>\n                <key>spriteSize</key>\n                <string>{123,148}</string>\n                <key>spriteSourceSize</key>\n                <string>{123,148}</string>\n                <key>textureRect</key>\n                <string>{{1,244},{123,148}}</string>\n                <key>textureRotated</key>\n                <false/>\n            </dict>\n            <key>cake-images-cake_4_3.png</key>\n            <dict>\n                <key>aliases</key>\n                <array/>\n                <key>spriteOffset</key>\n                <string>{0,0}</string>\n                <key>spriteSize</key>\n                <string>{123,148}</string>\n                <key>spriteSourceSize</key>\n                <string>{123,148}</string>\n                <key>textureRect</key>\n                <string>{{186,263},{123,148}}</string>\n                <key>textureRotated</key>\n                <false/>\n            </dict>\n            <key>cake-images-cake_goal.png</key>\n            <dict>\n                <key>aliases</key>\n                <array/>\n                <key>spriteOffset</key>\n                <string>{0,0}</string>\n                <key>spriteSize</key>\n                <string>{123,127}</string>\n                <key>spriteSourceSize</key>\n                <string>{123,127}</string>\n                <key>textureRect</key>\n                <string>{{126,413},{123,127}}</string>\n                <key>textureRotated</key>\n                <false/>\n            </dict>\n            <key>cake-images-plate.png</key>\n            <dict>\n                <key>aliases</key>\n                <array/>\n                <key>spriteOffset</key>\n                <string>{0,0}</string>\n                <key>spriteSize</key>\n                <string>{241,241}</string>\n                <key>spriteSourceSize</key>\n                <string>{241,241}</string>\n                <key>textureRect</key>\n                <string>{{1,1},{241,241}}</string>\n                <key>textureRotated</key>\n                <false/>\n            </dict>\n            <key>cake_1_1.png</key>\n            <dict>\n                <key>aliases</key>\n                <array/>\n                <key>spriteOffset</key>\n                <string>{0,0}</string>\n                <key>spriteSize</key>\n                <string>{124,129}</string>\n                <key>spriteSourceSize</key>\n                <string>{124,129}</string>\n                <key>textureRect</key>\n                <string>{{244,1},{124,129}}</string>\n                <key>textureRotated</key>\n                <false/>\n            </dict>\n            <key>cake_1_2.png</key>\n            <dict>\n                <key>aliases</key>\n                <array/>\n                <key>spriteOffset</key>\n                <string>{0,0}</string>\n                <key>spriteSize</key>\n                <string>{124,129}</string>\n                <key>spriteSourceSize</key>\n                <string>{124,129}</string>\n                <key>textureRect</key>\n                <string>{{370,1},{124,129}}</string>\n                <key>textureRotated</key>\n                <false/>\n            </dict>\n            <key>cake_1_3.png</key>\n            <dict>\n                <key>aliases</key>\n                <array/>\n                <key>spriteOffset</key>\n                <string>{0,0}</string>\n                <key>spriteSize</key>\n                <string>{124,129}</string>\n                <key>spriteSourceSize</key>\n                <string>{124,129}</string>\n                <key>textureRect</key>\n                <string>{{244,132},{124,129}}</string>\n                <key>textureRotated</key>\n                <false/>\n            </dict>\n            <key>cake_2_1.png</key>\n            <dict>\n                <key>aliases</key>\n                <array/>\n                <key>spriteOffset</key>\n                <string>{0,0}</string>\n                <key>spriteSize</key>\n                <string>{123,127}</string>\n                <key>spriteSourceSize</key>\n                <string>{123,127}</string>\n                <key>textureRect</key>\n                <string>{{1,394},{123,127}}</string>\n                <key>textureRotated</key>\n                <false/>\n            </dict>\n            <key>cake_2_2.png</key>\n            <dict>\n                <key>aliases</key>\n                <array/>\n                <key>spriteOffset</key>\n                <string>{0,0}</string>\n                <key>spriteSize</key>\n                <string>{123,127}</string>\n                <key>spriteSourceSize</key>\n                <string>{123,127}</string>\n                <key>textureRect</key>\n                <string>{{311,282},{123,127}}</string>\n                <key>textureRotated</key>\n                <false/>\n            </dict>\n            <key>cake_2_3.png</key>\n            <dict>\n                <key>aliases</key>\n                <array/>\n                <key>spriteOffset</key>\n                <string>{0,0}</string>\n                <key>spriteSize</key>\n                <string>{123,127}</string>\n                <key>spriteSourceSize</key>\n                <string>{123,127}</string>\n                <key>textureRect</key>\n                <string>{{311,411},{123,127}}</string>\n                <key>textureRotated</key>\n                <false/>\n            </dict>\n            <key>cake_3_1.png</key>\n            <dict>\n                <key>aliases</key>\n                <array/>\n                <key>spriteOffset</key>\n                <string>{0,0}</string>\n                <key>spriteSize</key>\n                <string>{122,150}</string>\n                <key>spriteSourceSize</key>\n                <string>{122,150}</string>\n                <key>textureRect</key>\n                <string>{{1,523},{122,150}}</string>\n                <key>textureRotated</key>\n                <false/>\n            </dict>\n            <key>cake_3_2.png</key>\n            <dict>\n                <key>aliases</key>\n                <array/>\n                <key>spriteOffset</key>\n                <string>{0,0}</string>\n                <key>spriteSize</key>\n                <string>{122,150}</string>\n                <key>spriteSourceSize</key>\n                <string>{122,150}</string>\n                <key>textureRect</key>\n                <string>{{251,540},{122,150}}</string>\n                <key>textureRotated</key>\n                <false/>\n            </dict>\n            <key>cake_3_3.png</key>\n            <dict>\n                <key>aliases</key>\n                <array/>\n                <key>spriteOffset</key>\n                <string>{0,0}</string>\n                <key>spriteSize</key>\n                <string>{122,150}</string>\n                <key>spriteSourceSize</key>\n                <string>{122,150}</string>\n                <key>textureRect</key>\n                <string>{{125,542},{122,150}}</string>\n                <key>textureRotated</key>\n                <false/>\n            </dict>\n            <key>cake_4_1.png</key>\n            <dict>\n                <key>aliases</key>\n                <array/>\n                <key>spriteOffset</key>\n                <string>{0,0}</string>\n                <key>spriteSize</key>\n                <string>{123,148}</string>\n                <key>spriteSourceSize</key>\n                <string>{123,148}</string>\n                <key>textureRect</key>\n                <string>{{370,132},{123,148}}</string>\n                <key>textureRotated</key>\n                <false/>\n            </dict>\n            <key>cake_4_2.png</key>\n            <dict>\n                <key>aliases</key>\n                <array/>\n                <key>spriteOffset</key>\n                <string>{0,0}</string>\n                <key>spriteSize</key>\n                <string>{123,148}</string>\n                <key>spriteSourceSize</key>\n                <string>{123,148}</string>\n                <key>textureRect</key>\n                <string>{{1,244},{123,148}}</string>\n                <key>textureRotated</key>\n                <false/>\n            </dict>\n            <key>cake_4_3.png</key>\n            <dict>\n                <key>aliases</key>\n                <array/>\n                <key>spriteOffset</key>\n                <string>{0,0}</string>\n                <key>spriteSize</key>\n                <string>{123,148}</string>\n                <key>spriteSourceSize</key>\n                <string>{123,148}</string>\n                <key>textureRect</key>\n                <string>{{186,263},{123,148}}</string>\n                <key>textureRotated</key>\n                <false/>\n            </dict>\n            <key>cake_goal.png</key>\n            <dict>\n                <key>aliases</key>\n                <array/>\n                <key>spriteOffset</key>\n                <string>{0,0}</string>\n                <key>spriteSize</key>\n                <string>{123,127}</string>\n                <key>spriteSourceSize</key>\n                <string>{123,127}</string>\n                <key>textureRect</key>\n                <string>{{126,413},{123,127}}</string>\n                <key>textureRotated</key>\n                <false/>\n            </dict>\n            <key>cake_splash.png</key>\n            <dict>\n                <key>aliases</key>\n                <array/>\n                <key>spriteOffset</key>\n                <string>{0,0}</string>\n                <key>spriteSize</key>\n                <string>{58,70}</string>\n                <key>spriteSourceSize</key>\n                <string>{58,70}</string>\n                <key>textureRect</key>\n                <string>{{126,244},{58,70}}</string>\n                <key>textureRotated</key>\n                <false/>\n            </dict>\n            <key>plate.png</key>\n            <dict>\n                <key>aliases</key>\n                <array/>\n                <key>spriteOffset</key>\n                <string>{0,0}</string>\n                <key>spriteSize</key>\n                <string>{241,241}</string>\n                <key>spriteSourceSize</key>\n                <string>{241,241}</string>\n                <key>textureRect</key>\n                <string>{{1,1},{241,241}}</string>\n                <key>textureRotated</key>\n                <false/>\n            </dict>\n        </dict>\n        <key>metadata</key>\n        <dict>\n            <key>format</key>\n            <integer>3</integer>\n            <key>pixelFormat</key>\n            <string>RGBA8888</string>\n            <key>premultiplyAlpha</key>\n            <false/>\n            <key>realTextureFileName</key>\n            <string>cake-93d6d57fba.png</string>\n            <key>size</key>\n            <string>{512,1024}</string>\n            <key>textureFileName</key>\n            <string>cake-93d6d57fba.png</string>\n        </dict>\n    </dict>\n</plist>\n","atlas":"\ncake-93d6d57fba.png\nsize: 512,1024\nformat: RGBA8888\nfilter: Linear,Linear\nrepeat: none\ncake-images-cake_1_1\n  rotate: false\n  xy: 244, 1\n  size: 124, 129\n  orig: 124, 129\n  offset: 0, 0\n  index: -1\ncake-images-cake_1_2\n  rotate: false\n  xy: 370, 1\n  size: 124, 129\n  orig: 124, 129\n  offset: 0, 0\n  index: -1\ncake-images-cake_1_3\n  rotate: false\n  xy: 244, 132\n  size: 124, 129\n  orig: 124, 129\n  offset: 0, 0\n  index: -1\ncake-images-cake_2_1\n  rotate: false\n  xy: 1, 394\n  size: 123, 127\n  orig: 123, 127\n  offset: 0, 0\n  index: -1\ncake-images-cake_2_2\n  rotate: false\n  xy: 311, 282\n  size: 123, 127\n  orig: 123, 127\n  offset: 0, 0\n  index: -1\ncake-images-cake_2_3\n  rotate: false\n  xy: 311, 411\n  size: 123, 127\n  orig: 123, 127\n  offset: 0, 0\n  index: -1\ncake-images-cake_3_1\n  rotate: false\n  xy: 1, 523\n  size: 122, 150\n  orig: 122, 150\n  offset: 0, 0\n  index: -1\ncake-images-cake_3_2\n  rotate: false\n  xy: 251, 540\n  size: 122, 150\n  orig: 122, 150\n  offset: 0, 0\n  index: -1\ncake-images-cake_3_3\n  rotate: false\n  xy: 125, 542\n  size: 122, 150\n  orig: 122, 150\n  offset: 0, 0\n  index: -1\ncake-images-cake_4_1\n  rotate: false\n  xy: 370, 132\n  size: 123, 148\n  orig: 123, 148\n  offset: 0, 0\n  index: -1\ncake-images-cake_4_2\n  rotate: false\n  xy: 1, 244\n  size: 123, 148\n  orig: 123, 148\n  offset: 0, 0\n  index: -1\ncake-images-cake_4_3\n  rotate: false\n  xy: 186, 263\n  size: 123, 148\n  orig: 123, 148\n  offset: 0, 0\n  index: -1\ncake-images-cake_goal\n  rotate: false\n  xy: 126, 413\n  size: 123, 127\n  orig: 123, 127\n  offset: 0, 0\n  index: -1\ncake-images-plate\n  rotate: false\n  xy: 1, 1\n  size: 241, 241\n  orig: 241, 241\n  offset: 0, 0\n  index: -1\ncake_1_1\n  rotate: false\n  xy: 244, 1\n  size: 124, 129\n  orig: 124, 129\n  offset: 0, 0\n  index: -1\ncake_1_2\n  rotate: false\n  xy: 370, 1\n  size: 124, 129\n  orig: 124, 129\n  offset: 0, 0\n  index: -1\ncake_1_3\n  rotate: false\n  xy: 244, 132\n  size: 124, 129\n  orig: 124, 129\n  offset: 0, 0\n  index: -1\ncake_2_1\n  rotate: false\n  xy: 1, 394\n  size: 123, 127\n  orig: 123, 127\n  offset: 0, 0\n  index: -1\ncake_2_2\n  rotate: false\n  xy: 311, 282\n  size: 123, 127\n  orig: 123, 127\n  offset: 0, 0\n  index: -1\ncake_2_3\n  rotate: false\n  xy: 311, 411\n  size: 123, 127\n  orig: 123, 127\n  offset: 0, 0\n  index: -1\ncake_3_1\n  rotate: false\n  xy: 1, 523\n  size: 122, 150\n  orig: 122, 150\n  offset: 0, 0\n  index: -1\ncake_3_2\n  rotate: false\n  xy: 251, 540\n  size: 122, 150\n  orig: 122, 150\n  offset: 0, 0\n  index: -1\ncake_3_3\n  rotate: false\n  xy: 125, 542\n  size: 122, 150\n  orig: 122, 150\n  offset: 0, 0\n  index: -1\ncake_4_1\n  rotate: false\n  xy: 370, 132\n  size: 123, 148\n  orig: 123, 148\n  offset: 0, 0\n  index: -1\ncake_4_2\n  rotate: false\n  xy: 1, 244\n  size: 123, 148\n  orig: 123, 148\n  offset: 0, 0\n  index: -1\ncake_4_3\n  rotate: false\n  xy: 186, 263\n  size: 123, 148\n  orig: 123, 148\n  offset: 0, 0\n  index: -1\ncake_goal\n  rotate: false\n  xy: 126, 413\n  size: 123, 127\n  orig: 123, 127\n  offset: 0, 0\n  index: -1\ncake_splash\n  rotate: false\n  xy: 126, 244\n  size: 58, 70\n  orig: 58, 70\n  offset: 0, 0\n  index: -1\nplate\n  rotate: false\n  xy: 1, 1\n  size: 241, 241\n  orig: 241, 241\n  offset: 0, 0\n  index: -1\n"}